{
  "general": {
    "gameLengthMin": 0,
    "dmg_to_champs_winner": 100,
    "dmg_to_obj_winner": 100,
    "vision_winner": 100,
    "cs_winner": 100,
    "champ_experience_winner": 100,
    "wards_placed_winner": 100,
    "gold_spender_winner": 100,
    "final_match_winner": 100
  },
  "per_team": {
    "100": {
      "total_gold_earned": 50066,
      "total_gold_spent": 41960,
      "team_comp": [
        {
          "champName": "TahmKench",
          "champId": 223
        },
        {
          "champName": "RekSai",
          "champId": 421
        },
        {
          "champName": "Vladimir",
          "champId": 8
        },
        {
          "champName": "Jhin",
          "champId": 202
        },
        {
          "champName": "Senna",
          "champId": 235
        }
      ],
      "total_baron_kills": 0,
      "total_dragon_kills": 3,
      "total_inhibitor_kils": 2,
      "total_kills": 43,
      "total_deaths": 14,
      "total_damage_dealt_to_champions": 79331,
      "total_damage_dealt_to_objectives": 61240,
      "total_damage_taken": 80004,
      "average_vision_score": 17,
      "total_wards_placed": 35,
      "average_creep_score": 82,
      "average_champion_experience": 9655,
      "dmg_carry": "RekSai",
      "obj_carry": "RekSai",
      "match_id": "NA1_4412248527"
    },
    "200": {
      "total_gold_earned": 36008,
      "total_gold_spent": 33830,
      "team_comp": [
        {
          "champName": "Irelia",
          "champId": 39
        },
        {
          "champName": "Volibear",
          "champId": 106
        },
        {
          "champName": "Veigar",
          "champId": 45
        },
        {
          "champName": "Twitch",
          "champId": 29
        },
        {
          "champName": "Yuumi",
          "champId": 350
        }
      ],
      "total_baron_kills": 0,
      "total_dragon_kills": 0,
      "total_inhibitor_kils": 0,
      "total_kills": 14,
      "total_deaths": 43,
      "total_damage_dealt_to_champions": 53584,
      "total_damage_dealt_to_objectives": 14920,
      "total_damage_taken": 92758,
      "average_vision_score": 14,
      "total_wards_placed": 33,
      "average_creep_score": 66,
      "average_champion_experience": 7478,
      "dmg_carry": "Irelia",
      "obj_carry": "Irelia",
      "match_id": "NA1_4412248527"
    }
  }
}